LICENSE
MANIFEST.in
README.md
setup.py
django_intlekt/__init__.py
django_intlekt/apps.py
django_intlekt/urls.py
django_intlekt.egg-info/PKG-INFO
django_intlekt.egg-info/SOURCES.txt
django_intlekt.egg-info/dependency_links.txt
django_intlekt.egg-info/requires.txt
django_intlekt.egg-info/top_level.txt
django_intlekt/models/__init__.py
django_intlekt/models/collections/__init__.py
django_intlekt/models/collections/collected_source.py
django_intlekt/models/collections/collection.py
django_intlekt/models/collections/document.py
django_intlekt/models/collections/post.py
django_intlekt/models/collections/source.py
django_intlekt/models/collections/source_driver.py
django_intlekt/models/collections/tag.py
django_intlekt/models/collections/utils.py
django_intlekt/models/library/__init__.py
django_intlekt/models/library/group.py
django_intlekt/models/library/text.py
django_intlekt/models/library/usl.py
django_intlekt/models/library/word.py
django_intlekt/serializers/__init__.py
django_intlekt/serializers/collections.py
django_intlekt/serializers/library.py
django_intlekt/serializers/utils.py
django_intlekt/static/intlekt/api.js
django_intlekt/static/intlekt/breadcrumb.js
django_intlekt/static/intlekt/collectedSourceCreatorScoopit.js
django_intlekt/static/intlekt/collectedSourcesListScoopit.js
django_intlekt/static/intlekt/collectionCreator.js
django_intlekt/static/intlekt/collectionEditor.js
django_intlekt/static/intlekt/collectionsImporterScoopit.js
django_intlekt/static/intlekt/collectionsList.js
django_intlekt/static/intlekt/documentEditor.js
django_intlekt/static/intlekt/jquery-3.2.1.min.js
django_intlekt/static/intlekt/jquery-ui.css
django_intlekt/static/intlekt/jquery-ui.js
django_intlekt/static/intlekt/list.min.js
django_intlekt/static/intlekt/postCreator.js
django_intlekt/static/intlekt/postEditor.js
django_intlekt/static/intlekt/postsList.css
django_intlekt/static/intlekt/postsList.js
django_intlekt/static/intlekt/sourceEditor.js
django_intlekt/static/intlekt/style.css
django_intlekt/static/intlekt/tabs.css
django_intlekt/static/intlekt/tabs.js
django_intlekt/static/intlekt/tagEditor.js
django_intlekt/static/intlekt/tools.js
