Metadata-Version: 1.1
Name: django-intlekt
Version: 0.3.0
Summary: Django app for Intlekt, a content curation application using the IEML language.
Home-page: https://github.com/IEMLdev/django-intlekt
Author: Vincent Lefoulon
Author-email: vincent.lefoulon@free.fr
License: GPLv3
Keywords: ieml intlekt semantic syntax language indexing
Platform: UNKNOWN
Classifier: Development Status :: 3 - Alpha
Classifier: License :: OSI Approved :: GNU General Public License v3 (GPLv3)
Classifier: Programming Language :: Python
Classifier: Programming Language :: Python :: 3.5
Classifier: Environment :: Web Environment
Classifier: Framework :: Django
Classifier: Intended Audience :: Developers
Classifier: Operating System :: OS Independent
Classifier: Topic :: Text Processing :: Linguistic
Classifier: Topic :: Text Processing :: Indexing
